univ_helper/__init__.py
univ_helper/module.py
univ_helper-1.0.0.dist-info/METADATA
univ_helper-1.0.0.dist-info/WHEEL
univ_helper-1.0.0.dist-info/top_level.txt
univ_helper-1.0.0.dist-info/RECORD
